quadratum/__init__.py
quadratum/functional.py
quadratum/transformer.py
quadratum/transforms.py
quadratum-0.2.1.dist-info/LICENSE
quadratum-0.2.1.dist-info/METADATA
quadratum-0.2.1.dist-info/WHEEL
quadratum-0.2.1.dist-info/top_level.txt
quadratum-0.2.1.dist-info/RECORD
